pyxu/__init__.py
pyxu/runtime.py
pyxu/abc/__init__.py
pyxu/abc/arithmetic.py
pyxu/abc/operator.py
pyxu/abc/solver.py
pyxu/contrib/__init__.py
pyxu/experimental/_dev/__init__.py
pyxu/experimental/sampler/__init__.py
pyxu/experimental/sampler/_sampler.py
pyxu/experimental/sampler/statistics.py
pyxu/info/config.py
pyxu/info/deps.py
pyxu/info/plugin.py
pyxu/info/ptype.py
pyxu/info/warning.py
pyxu/math/__init__.py
pyxu/math/linalg.py
pyxu/math/linesearch.py
pyxu/operator/__init__.py
pyxu/operator/blocks.py
pyxu/operator/misc.py
pyxu/operator/ufunc.py
pyxu/operator/func/README.rst
pyxu/operator/func/__init__.py
pyxu/operator/func/indicator.py
pyxu/operator/func/loss.py
pyxu/operator/func/norm.py
pyxu/operator/interop/__init__.py
pyxu/operator/interop/jax.py
pyxu/operator/interop/sciop.py
pyxu/operator/interop/source.py
pyxu/operator/interop/torch.py
pyxu/operator/linop/__init__.py
pyxu/operator/linop/base.py
pyxu/operator/linop/diff.py
pyxu/operator/linop/filter.py
pyxu/operator/linop/kron.py
pyxu/operator/linop/pad.py
pyxu/operator/linop/reduce.py
pyxu/operator/linop/select.py
pyxu/operator/linop/fft/czt.py
pyxu/operator/linop/fft/fft.py
pyxu/operator/linop/fft/filter.py
pyxu/operator/linop/stencil/_stencil.py
pyxu/operator/linop/stencil/_template_cpu.txt
pyxu/operator/linop/stencil/_template_gpu.txt
pyxu/operator/linop/stencil/stencil.py
pyxu/operator/map/__init__.py
pyxu/operator/map/base.py
pyxu/opt/stop.py
pyxu/opt/solver/__init__.py
pyxu/opt/solver/adam.py
pyxu/opt/solver/cg.py
pyxu/opt/solver/nlcg.py
pyxu/opt/solver/pds.py
pyxu/opt/solver/pgd.py
pyxu/util/__init__.py
pyxu/util/array_module.py
pyxu/util/cache.py
pyxu/util/complex.py
pyxu/util/io.py
pyxu/util/misc.py
pyxu/util/operator.py
pyxu-2.0.3.dist-info/METADATA
pyxu-2.0.3.dist-info/WHEEL
pyxu-2.0.3.dist-info/licenses/LICENSE
pyxu-2.0.3.dist-info/RECORD
