Metadata-Version: 2.4
Name: pyxu
Version: 2.0.3
Summary: Modular and scalable computational imaging in Python with support for GPU/out-of-core computing.
Project-URL: download, https://github.com/pyxu-org/pyxu
Project-URL: homepage, https://pyxu-org.github.io/
Author: S. Kashani, J. Rué-Queralt, M. Simeoni, Pyxu Developers
Author-email: contact@pyxu.org
License-Expression: MIT
License-File: LICENSE
Classifier: Development Status :: 5 - Production/Stable
Classifier: Intended Audience :: Science/Research
Classifier: License :: OSI Approved :: MIT License
Classifier: Programming Language :: Python :: 3.10
Classifier: Programming Language :: Python :: 3.11
Classifier: Programming Language :: Python :: 3.12
Classifier: Programming Language :: Python :: Implementation :: CPython
Classifier: Topic :: Scientific/Engineering
Requires-Python: <3.13,>=3.10
Requires-Dist: cloudpickle<4,>=3.0.0
Requires-Dist: dask[array,diagnostics,distributed]<2024.9,>=2023.12
Requires-Dist: numba<1,>=0.59
Requires-Dist: numpy<2.1,>=1.24
Requires-Dist: packaging>=23.1
Requires-Dist: scipy<2,>=1.11
Requires-Dist: zarr<3,>=2.16
Provides-Extra: complete
Requires-Dist: cupy-cuda12x<14,>=13.0; extra == 'complete'
Requires-Dist: ipython<9,>=8.14; extra == 'complete'
Requires-Dist: jupyterlab<5,>=4.0; extra == 'complete'
Requires-Dist: matplotlib<4,>=3.7; extra == 'complete'
Provides-Extra: complete-cpu
Requires-Dist: ipython<9,>=8.14; extra == 'complete-cpu'
Requires-Dist: jupyterlab<5,>=4.0; extra == 'complete-cpu'
Requires-Dist: matplotlib<4,>=3.7; extra == 'complete-cpu'
Provides-Extra: complete11
Requires-Dist: cupy-cuda11x<14,>=13.0; extra == 'complete11'
Requires-Dist: ipython<9,>=8.14; extra == 'complete11'
Requires-Dist: jupyterlab<5,>=4.0; extra == 'complete11'
Requires-Dist: matplotlib<4,>=3.7; extra == 'complete11'
Provides-Extra: complete12
Requires-Dist: cupy-cuda12x<14,>=13.0; extra == 'complete12'
Requires-Dist: ipython<9,>=8.14; extra == 'complete12'
Requires-Dist: jupyterlab<5,>=4.0; extra == 'complete12'
Requires-Dist: matplotlib<4,>=3.7; extra == 'complete12'
Provides-Extra: dev
Requires-Dist: graphviz<1,>=0.20; extra == 'dev'
Requires-Dist: hatch<2,>=1.7; extra == 'dev'
Requires-Dist: ipython<9,>=8.14; extra == 'dev'
Requires-Dist: jupyterlab<5,>=4.0; extra == 'dev'
Requires-Dist: matplotlib<4,>=3.7; extra == 'dev'
Requires-Dist: nbsphinx<1,>=0.9.0; extra == 'dev'
Requires-Dist: pre-commit<4,>=3.3; extra == 'dev'
Requires-Dist: pydata-sphinx-theme==0.13.3; extra == 'dev'
Requires-Dist: pytest<8,>=7.4; extra == 'dev'
Requires-Dist: scikit-image<1,>=0.21; extra == 'dev'
Requires-Dist: sphinx-codeautolink<1,>=0.15.0; extra == 'dev'
Requires-Dist: sphinx-copybutton<1,>=0.5.2; extra == 'dev'
Requires-Dist: sphinx-design<1,>=0.4.1; extra == 'dev'
Requires-Dist: sphinx-gallery<1,>=0.17.0; extra == 'dev'
Requires-Dist: sphinx-togglebutton<1,>=0.3.2; extra == 'dev'
Requires-Dist: sphinx<8,>=7.2; extra == 'dev'
Requires-Dist: tox<5,>=4.6; extra == 'dev'
Provides-Extra: gpu11-base
Requires-Dist: cupy-cuda11x<14,>=13.0; extra == 'gpu11-base'
Provides-Extra: gpu12-base
Requires-Dist: cupy-cuda12x<14,>=13.0; extra == 'gpu12-base'
Provides-Extra: interact
Requires-Dist: ipython<9,>=8.14; extra == 'interact'
Requires-Dist: jupyterlab<5,>=4.0; extra == 'interact'
Requires-Dist: matplotlib<4,>=3.7; extra == 'interact'
